MANIFEST.in
README.md
rop.py
setup.py
read_only_property.egg-info/PKG-INFO
read_only_property.egg-info/SOURCES.txt
read_only_property.egg-info/dependency_links.txt
read_only_property.egg-info/top_level.txt