Metadata-Version: 1.1
Name: read-only-property
Version: 0.1
Summary: Create class properties which can't be changed.
Home-page: https://github.com/oz123/read-only-properties.git
Author: Oz Tiram
Author-email: oz.tiram@gmail.com
License: Python Software Foundation Lincese
Platform: any
Classifier: Development Status :: 4 - Beta
Classifier: Intended Audience :: Developers
Classifier: License :: OSI Approved :: Python Software Foundation License
Classifier: Programming Language :: Python :: 2.7
Classifier: Programming Language :: Python :: 3
Classifier: Programming Language :: Python :: 3.4
Classifier: Programming Language :: Python :: 3.5
Classifier: Programming Language :: Python :: 3.6
